iotssuetsample/__init__.py
iotssuetsample-0.1.dist-info/METADATA
iotssuetsample-0.1.dist-info/WHEEL
iotssuetsample-0.1.dist-info/top_level.txt
iotssuetsample-0.1.dist-info/RECORD
