Metadata-Version: 2.1
Name: iotssuetsample
Version: 0.1
Summary: this is a package
Home-page: UNKNOWN
Author: Sir Qasim and Syed Muhammad Mooazam
Author-email: UNKNOWN
License: UNKNOWN
Platform: UNKNOWN
